setup.py
daction/__init__.py
daction/daction.py
daction/main.py
daction.egg-info/PKG-INFO
daction.egg-info/SOURCES.txt
daction.egg-info/dependency_links.txt
daction.egg-info/entry_points.txt
daction.egg-info/not-zip-safe
daction.egg-info/top_level.txt