Metadata-Version: 1.1
Name: daction
Version: 0.7.5
Summary: Performs custom action on all/specified elements in the directory.
Home-page: https://github.com/massanchik/daction
Author: Ashot Seropian
Author-email: ashot.seropyan@gmail.com
License: MIT
Keywords: daction,action,directory,generate,path,command,pattern
Platform: UNKNOWN
Classifier: Development Status :: 5 - Production/Stable
Classifier: Intended Audience :: Developers
Classifier: License :: OSI Approved :: MIT License
Classifier: Environment :: Console
Classifier: Topic :: Software Development :: Code Generators
Classifier: Programming Language :: Python
Classifier: Programming Language :: Python :: 3
Classifier: Programming Language :: Python :: 3.2
Classifier: Programming Language :: Python :: 3.3
Classifier: Programming Language :: Python :: 3.4
